AUTHORS
CHANGES
README
setup.py
debug_toolbar_extra/__init__.py
debug_toolbar_extra/panels.py
debug_toolbar_extra/templates/debug_toolbar_extra/panels/print_template_name_panel.html
django_debug_toolbar_extra.egg-info/PKG-INFO
django_debug_toolbar_extra.egg-info/SOURCES.txt
django_debug_toolbar_extra.egg-info/dependency_links.txt
django_debug_toolbar_extra.egg-info/not-zip-safe
django_debug_toolbar_extra.egg-info/top_level.txt