Metadata-Version: 1.0
Name: django-debug-toolbar-extra
Version: 0.0.2
Summary: Django application that allows add funcionality to the django-debug-toolbar
Home-page: https://tracpub.yaco.es/djangoapps/wiki/DjangoDebugToolbarExtra
Author: Yaco Sistemas S.L.
Author-email: pmartin@yaco.es
License: LGPL 3
Keywords: django,debug toolbar,debug,toolbar,panels
Platform: UNKNOWN
Classifier: Development Status :: 4 - Beta
Classifier: Framework :: Django
Classifier: License :: OSI Approved :: GNU Library or Lesser General Public License (LGPL)
